farialimer/__init__.py
farialimer/parser.py
farialimer/specs/b3/imbarq014.yaml
farialimer/utils/__init__.py
farialimer/utils/converters.py
farialimer/utils/math_ops.py
farialimer-0.0.2a0.dist-info/LICENSE
farialimer-0.0.2a0.dist-info/METADATA
farialimer-0.0.2a0.dist-info/WHEEL
farialimer-0.0.2a0.dist-info/top_level.txt
farialimer-0.0.2a0.dist-info/RECORD
