Metadata-Version: 2.1
Name: farialimer
Version: 0.0.2a0
Summary: Parser for Brazilian Finance Documents. Ex: IMBARQ, CNAB
Author-email: Leandro Meili <leandro.meili@gmail.com>
License: MIT
Project-URL: repository, https://github.com/redlotus-dev/farialimer
Keywords: parser,imbarq,cnab
Classifier: Programming Language :: Python :: 3
Requires-Python: >=3.7
License-File: LICENSE
Requires-Dist: PyYAML
